ntsl/__init__.py
ntsl/exceptions.py
ntsl/main.py
ntsl-0.1.1.dist-info/METADATA
ntsl-0.1.1.dist-info/WHEEL
ntsl-0.1.1.dist-info/top_level.txt
ntsl-0.1.1.dist-info/RECORD
